averagepackage_sanwariyia/__init__.py
averagepackage_sanwariyia/avg.py
averagepackage_sanwariyia-0.0.3.dist-info/METADATA
averagepackage_sanwariyia-0.0.3.dist-info/WHEEL
averagepackage_sanwariyia-0.0.3.dist-info/licenses/LICENSE.txt
averagepackage_sanwariyia-0.0.3.dist-info/RECORD
