Metadata-Version: 2.1
Name: averagepackage_sanwariyia
Version: 0.0.3
Summary: To find avg
Author-email: Sanwariyia S <sanwariyia@gmail.com>
License-File: LICENSE.txt
Classifier: License :: OSI Approved :: MIT License
Classifier: Operating System :: OS Independent
Classifier: Programming Language :: Python :: 3
Requires-Python: >=3.7
